setuptools_cythonize.py
setuptools_cythonize-1.0.7.dist-info/LICENSE
setuptools_cythonize-1.0.7.dist-info/METADATA
setuptools_cythonize-1.0.7.dist-info/WHEEL
setuptools_cythonize-1.0.7.dist-info/top_level.txt
setuptools_cythonize-1.0.7.dist-info/RECORD
