Metadata-Version: 2.1
Name: setuptools-cythonize
Version: 1.0.7
Summary: Distribute python modules/packages as binary files (compilation based on Cython)
Home-page: https://github.com/anxuae/setuptools-cythonize
Author: Antoine Rousseaux
License: MIT license
Download-URL: https://github.com/anxuae/setuptools-cythonize/archive/1.0.7.tar.gz
Keywords: setup,install,compilation
Platform: unix
Platform: linux
Platform: darwin
Platform: win32
Classifier: Development Status :: 5 - Production/Stable
Classifier: Environment :: Other Environment
Classifier: Intended Audience :: Developers
Classifier: License :: OSI Approved :: MIT License
Classifier: Operating System :: POSIX :: Linux
Classifier: Programming Language :: Python :: 2.7
Classifier: Programming Language :: Python :: 3.4
Classifier: Programming Language :: Python :: 3.5
Classifier: Natural Language :: English
Classifier: Topic :: System :: Installation/Setup
License-File: LICENSE
